NiukeShichangGangQiuzhiJingyanFenxiang20212022Fix1/README.md
NiukeShichangGangQiuzhiJingyanFenxiang20212022Fix1/__init__.py
NiukeShichangGangQiuzhiJingyanFenxiang20212022Fix1/__main__.py
NiukeShichangGangQiuzhiJingyanFenxiang20212022Fix1/file.epub
NiukeShichangGangQiuzhiJingyanFenxiang20212022Fix1/index.html
NiukeShichangGangQiuzhiJingyanFenxiang20212022Fix1/css/__init__.py
NiukeShichangGangQiuzhiJingyanFenxiang20212022Fix1/css/annotations.css
NiukeShichangGangQiuzhiJingyanFenxiang20212022Fix1/css/main.css
NiukeShichangGangQiuzhiJingyanFenxiang20212022Fix1/css/normalize.css
NiukeShichangGangQiuzhiJingyanFenxiang20212022Fix1/css/popup.css
NiukeShichangGangQiuzhiJingyanFenxiang20212022Fix1/font/__init__.py
NiukeShichangGangQiuzhiJingyanFenxiang20212022Fix1/font/fontello.eot
NiukeShichangGangQiuzhiJingyanFenxiang20212022Fix1/font/fontello.svg
NiukeShichangGangQiuzhiJingyanFenxiang20212022Fix1/font/fontello.ttf
NiukeShichangGangQiuzhiJingyanFenxiang20212022Fix1/font/fontello.woff
NiukeShichangGangQiuzhiJingyanFenxiang20212022Fix1/img/__init__.py
NiukeShichangGangQiuzhiJingyanFenxiang20212022Fix1/img/annotator-glyph-sprite.png
NiukeShichangGangQiuzhiJingyanFenxiang20212022Fix1/img/annotator-icon-sprite.png
NiukeShichangGangQiuzhiJingyanFenxiang20212022Fix1/img/apple-touch-icon.png
NiukeShichangGangQiuzhiJingyanFenxiang20212022Fix1/img/cancelfullscreen.png
NiukeShichangGangQiuzhiJingyanFenxiang20212022Fix1/img/close.png
NiukeShichangGangQiuzhiJingyanFenxiang20212022Fix1/img/fullscreen.png
NiukeShichangGangQiuzhiJingyanFenxiang20212022Fix1/img/loader.gif
NiukeShichangGangQiuzhiJingyanFenxiang20212022Fix1/img/menu-icon.png
NiukeShichangGangQiuzhiJingyanFenxiang20212022Fix1/img/save.png
NiukeShichangGangQiuzhiJingyanFenxiang20212022Fix1/img/saved.png
NiukeShichangGangQiuzhiJingyanFenxiang20212022Fix1/img/settings-s.png
NiukeShichangGangQiuzhiJingyanFenxiang20212022Fix1/img/settings.png
NiukeShichangGangQiuzhiJingyanFenxiang20212022Fix1/img/star.png
niuke_shichang_gang_qiuzhi_jingyan_fenxiang_2021_2022_fix1-2025.3.25.1.dist-info/METADATA
niuke_shichang_gang_qiuzhi_jingyan_fenxiang_2021_2022_fix1-2025.3.25.1.dist-info/WHEEL
niuke_shichang_gang_qiuzhi_jingyan_fenxiang_2021_2022_fix1-2025.3.25.1.dist-info/entry_points.txt
niuke_shichang_gang_qiuzhi_jingyan_fenxiang_2021_2022_fix1-2025.3.25.1.dist-info/top_level.txt
niuke_shichang_gang_qiuzhi_jingyan_fenxiang_2021_2022_fix1-2025.3.25.1.dist-info/RECORD
